{
  "name": "animated-table-demo",
  "type": "registry:example",
  "registryDependencies": [
    "animated-table"
  ],
  "files": [
    {
      "path": "examples/animated-table-demo.tsx",
      "content": "import { Badge } from \"@/components/ui/badge\";\nimport { AnimatedTable, ColumnDef } from \"@/registry/default/ui/animated-table\";\nimport { Avatar, AvatarFallback, AvatarImage } from \"@/components/ui/avatar\";\nimport * as React from \"react\";\n\ninterface User {\n  id: number;\n  name: string;\n  email: string;\n  role: string;\n  status: \"active\" | \"inactive\";\n  avatar?: string;\n  lastLogin: string;\n}\n\nconst sampleData: User[] = [\n  {\n    id: 1,\n    name: \"John Doe\",\n    email: \"john@example.com\",\n    role: \"Admin\",\n    status: \"active\",\n    avatar: \"https://github.com/shadcn.png\",\n    lastLogin: \"2024-01-15\",\n  },\n  {\n    id: 2,\n    name: \"Jane Smith\",\n    email: \"jane@example.com\",\n    role: \"User\",\n    status: \"active\",\n    avatar: \"https://github.com/vercel.png\",\n    lastLogin: \"2024-01-14\",\n  },\n  {\n    id: 3,\n    name: \"Bob Johnson\",\n    email: \"bob@example.com\",\n    role: \"Moderator\",\n    status: \"inactive\",\n    lastLogin: \"2024-01-10\",\n  },\n  {\n    id: 4,\n    name: \"Alice Brown\",\n    email: \"alice@example.com\",\n    role: \"User\",\n    status: \"active\",\n    lastLogin: \"2024-01-13\",\n  },\n  {\n    id: 5,\n    name: \"Charlie Wilson\",\n    email: \"charlie@example.com\",\n    role: \"Admin\",\n    status: \"active\",\n    avatar: \"https://github.com/timneutkens.png\",\n    lastLogin: \"2024-01-12\",\n  },\n];\n\nconst columns: ColumnDef<User>[] = [\n  {\n    id: \"name\",\n    header: \"Name\",\n    accessorKey: \"name\",\n    sortable: true,\n    cell: (user) => (\n      <div className=\"flex items-center gap-3\">\n        <Avatar className=\"h-8 w-8\">\n          <AvatarImage src={user.avatar} alt={user.name} />\n          <AvatarFallback>\n            {user.name\n              .split(\" \")\n              .map((n) => n[0])\n              .join(\"\")}\n          </AvatarFallback>\n        </Avatar>\n        <div>\n          <div className=\"font-medium\">{user.name}</div>\n          <div className=\"text-sm text-muted-foreground\">{user.email}</div>\n        </div>\n      </div>\n    ),\n  },\n  {\n    id: \"role\",\n    header: \"Role\",\n    accessorKey: \"role\",\n    sortable: true,\n    cell: (row) => (\n      <Badge variant={row.role === \"Admin\" ? \"default\" : \"secondary\"}>\n        {row.role}\n      </Badge>\n    ),\n  },\n  {\n    id: \"status\",\n    header: \"Status\",\n    accessorKey: \"status\",\n    sortable: true,\n    cell: (row) => (\n      <Badge variant={row.status === \"active\" ? \"default\" : \"destructive\"}>\n        {row.status}\n      </Badge>\n    ),\n  },\n  {\n    id: \"lastLogin\",\n    header: \"Last Login\",\n    accessorKey: \"lastLogin\",\n    sortable: true,\n  },\n];\n\nexport default function AnimatedTableDemo() {\n  const [selectedIds, setSelectedIds] = React.useState<(string | number)[]>([]);\n  const [sortColumn, setSortColumn] = React.useState<string>(\"\");\n  const [sortDirection, setSortDirection] = React.useState<\"asc\" | \"desc\" | null>(null);\n  const [searchValue, setSearchValue] = React.useState(\"\");\n\n  // Filter and sort data\n  const filteredData = React.useMemo(() => {\n    let filtered = sampleData;\n\n    // Apply search filter\n    if (searchValue) {\n      filtered = filtered.filter(\n        (user) =>\n          user.name.toLowerCase().includes(searchValue.toLowerCase()) ||\n          user.email.toLowerCase().includes(searchValue.toLowerCase()) ||\n          user.role.toLowerCase().includes(searchValue.toLowerCase())\n      );\n    }\n\n    // Apply sorting\n    if (sortColumn && sortDirection) {\n      filtered = [...filtered].sort((a, b) => {\n        const aValue = a[sortColumn as keyof User];\n        const bValue = b[sortColumn as keyof User];\n\n        if (aValue < bValue) return sortDirection === \"asc\" ? -1 : 1;\n        if (aValue > bValue) return sortDirection === \"asc\" ? 1 : -1;\n        return 0;\n      });\n    }\n\n    return filtered;\n  }, [searchValue, sortColumn, sortDirection]);\n\n  const handleSort = (columnId: string, direction: \"asc\" | \"desc\" | null) => {\n    setSortColumn(columnId);\n    setSortDirection(direction);\n  };\n\n  const handleSelectionChange = (ids: (string | number)[]) => {\n    setSelectedIds(ids);\n  };\n\n  return (\n    <div className=\"flex flex-col gap-3\">\n      <h3 className=\"font-medium text-sm\">Animated Table</h3>\n      <AnimatedTable\n        data={filteredData}\n        columns={columns}\n        selectable\n        selectedIds={selectedIds}\n        onSelectionChange={handleSelectionChange}\n        sortColumn={sortColumn}\n        sortDirection={sortDirection}\n        onSort={handleSort}\n        searchable\n        searchValue={searchValue}\n        onSearchChange={setSearchValue}\n        searchPlaceholder=\"Search users...\"\n        columnVisibility\n        expandable\n        renderExpandedRow={(row) => (\n          <div className=\"space-y-2\">\n            <h4 className=\"font-medium\">User Details</h4>\n            <p className=\"text-sm text-muted-foreground\">\n              Full details for {row.name} would go here.\n            </p>\n          </div>\n        )}\n        striped\n        stickyHeader\n      />\n    </div>\n  );\n}",
      "type": "registry:example",
      "target": ""
    }
  ]
}